sen2vec/__init__.py
sen2vec/sen2vec.py
sen2vec/models/__init__.py
sen2vec/models/__main__.pyd
sen2vec/models/__main__.so
sen2vec/models/bert.pyd
sen2vec/models/bert.so
sen2vec/models/file_utils.pyd
sen2vec/models/file_utils.so
sen2vec/models/modeling.pyd
sen2vec/models/modeling.so
sen2vec/models/tokenization.py
sen2vec/sampled/__init__.py
sen2vec/sampled/downloader.py
sen2vec/sampled/bertwwm_pretrain/added_tokens.json
sen2vec/sampled/bertwwm_pretrain/config.json
sen2vec/sampled/bertwwm_pretrain/model_config.txt
sen2vec/sampled/bertwwm_pretrain/scaler.csv
sen2vec/sampled/bertwwm_pretrain/special_tokens_map.json
sen2vec/sampled/bertwwm_pretrain/tokenizer_config.json
sen2vec/sampled/bertwwm_pretrain/vocab.txt
sen2vec/util/__init__.py
sen2vec/util/tools.py
sen2vec/util/utils.py
sen2vec-1.88.dist-info/LICENSE
sen2vec-1.88.dist-info/METADATA
sen2vec-1.88.dist-info/WHEEL
sen2vec-1.88.dist-info/top_level.txt
sen2vec-1.88.dist-info/RECORD
