Metadata-Version: 2.1
Name: sen2vec
Version: 1.88
Summary: - A sen2vec MODEL that can transform sentence to vector, for Finance mainly, pytorch needed.
Author: xczcx
Author-email: 2292879219@qq.com
Requires-Python: ==3.7
License-File: LICENSE
